idom_dash/IdomDashComponent.py
idom_dash/__init__.py
idom_dash/_imports_.py
idom_dash/idom_compat.py
idom_dash/idom_dash.min.js
idom_dash/idom_dash.min.js.map
idom_dash/metadata.json
idom_dash/package-info.json
idom_dash-0.1.0.dist-info/LICENSE
idom_dash-0.1.0.dist-info/METADATA
idom_dash-0.1.0.dist-info/WHEEL
idom_dash-0.1.0.dist-info/top_level.txt
idom_dash-0.1.0.dist-info/RECORD
