Metadata-Version: 2.1
Name: idom-dash
Version: 0.1.0
Summary: A custom component for Dash that uses IDOM
Author: Ryan Morshead <ryan.morshead@gmail.com>
License: MIT
Classifier: Framework :: Dash
License-File: LICENSE
Requires-Dist: idom[flask] (<0.42,>=0.41)
